aioredux/__init__.py
aioredux/core.py
aioredux/middleware.py
aioredux/utils.py
aioredux/tests/__init__.py
aioredux/tests/base.py
aioredux/tests/test_basic.py
aioredux/tests/test_thunk.py
aioredux/tests/test_thunk_nested.py
aioredux-1.1.0.dist-info/DESCRIPTION.rst
aioredux-1.1.0.dist-info/METADATA
aioredux-1.1.0.dist-info/RECORD
aioredux-1.1.0.dist-info/WHEEL
aioredux-1.1.0.dist-info/metadata.json
aioredux-1.1.0.dist-info/pbr.json
aioredux-1.1.0.dist-info/top_level.txt
