Metadata-Version: 2.0
Name: aioredux
Version: 1.1.0
Summary: Pythonic redux
Home-page: https://github.com/ariddell/aioredux
Author: aioredux developers
Author-email: aioredux-developers@example.net
License: UNKNOWN
Platform: UNKNOWN
Classifier: License :: OSI Approved :: Mozilla Public License 2.0 (MPL 2.0)
Classifier: Operating System :: POSIX :: Linux
Classifier: Programming Language :: Python
Classifier: Programming Language :: Python :: 3
Classifier: Programming Language :: Python :: 3.4
Requires-Dist: pbr (<2.0,>=1.4)
Requires-Dist: toolz (>=0.7.4)
